Logger/Logger.py
Logger/__init__.py
plain_logger/Logger.py
plain_logger/__init__.py
plain_logger-0.1.5.dist-info/LICENSE.txt
plain_logger-0.1.5.dist-info/METADATA
plain_logger-0.1.5.dist-info/WHEEL
plain_logger-0.1.5.dist-info/top_level.txt
plain_logger-0.1.5.dist-info/RECORD
