Metadata-Version: 2.1
Name: plain-logger
Version: 0.1.5
Summary: An easy to use helper pip package to help you log details at any point in code.
Home-page: https://github.com/prapanw/plain_logger
Author: Prakhar Panwaria
Author-email: prapanw@microsoft.com
License: MIT
Download-URL: https://github.com/prapanw/plain_logger
Keywords: logger logging loginfo logwarning logerror logdebug
Platform: UNKNOWN
Classifier: Programming Language :: Python :: 3
Classifier: License :: OSI Approved :: MIT License
Classifier: Operating System :: OS Independent
